fhnw_thermo_tools/__init__.py
fhnw_thermo_tools/feuchte_luft/FeuchteLuft.py
fhnw_thermo_tools/feuchte_luft/__init__.py
fhnw_thermo_tools/feuchte_luft/calculations.py
fhnw_thermo_tools/feuchte_luft/plotting.py
fhnw_thermo_tools-0.0.9.dist-info/LICENSE.txt
fhnw_thermo_tools-0.0.9.dist-info/METADATA
fhnw_thermo_tools-0.0.9.dist-info/WHEEL
fhnw_thermo_tools-0.0.9.dist-info/top_level.txt
fhnw_thermo_tools-0.0.9.dist-info/RECORD
