Metadata-Version: 2.1
Name: fhnw-thermo-tools
Version: 0.0.9
Author: Raffael Schreiber
Author-email: raffaelmichael.schreiber@fhnw.ch
License-File: LICENSE.txt
Requires-Dist: numpy ~=1.26.1
Requires-Dist: matplotlib ~=3.8.0
Requires-Dist: coolprop ==6.5.0.post1
